{
    "6705893c-84e8-79c3-c4f1-ec4f57e01c6c": {
        "paletteKey": "FlexLayoutRow",
        "commentid": null,
        "designerReference": [
            {
                "_key": "componentLabel",
                "_value": "Row",
                "_type": "kv",
                "_attrDef": "p",
                "_useAsLabel": true
            },
            {
                "_key": "style",
                "_value": "",
                "_type": "kv",
                "_attrDef": "p"
            },
            {
                "_key": "class",
                "_value": "",
                "_type": "dav",
                "_attrDef": "p"
            },
            {
                "_key": "fxFlex",
                "_value": "",
                "_type": "kv",
                "_attrDef": "p"
            },
            {
                "_key": "fxLayoutGap",
                "_value": "",
                "_type": "kv",
                "_attrDef": "p"
            },
            {
                "_key": "wrap",
                "_value": "wrap",
                "_type": "a",
                "_attrDef": "p"
            },
            {
                "_key": "layoutAlign",
                "_value": "center",
                "_type": "a",
                "_attrDef": "p"
            },
            {
                "_key": "pLayoutAlign",
                "_value": "stretch",
                "_type": "a",
                "_attrDef": "p"
            },
            {
                "_key": "[fxShow]",
                "_value": "true",
                "_type": "kv",
                "_attrDef": "p"
            }
        ],
        "05c53111-bfaa-6d25-c7b1-8092e1286990": {
            "paletteKey": "NG-Form",
            "parentEditorKey": "6705893c-84e8-79c3-c4f1-ec4f57e01c6c",
            "commentid": null,
            "designerReference": [
                {
                    "_key": "componentLabel",
                    "_value": "Form",
                    "_type": "kv",
                    "_attrDef": "p",
                    "_useAsLabel": true
                },
                {
                    "_key": "style",
                    "_value": "",
                    "_type": "kv",
                    "_attrDef": "p"
                },
                {
                    "_key": "class",
                    "_value": "",
                    "_type": "dav",
                    "_attrDef": "p"
                },
                {
                    "_key": "action",
                    "_value": "",
                    "_type": "kv",
                    "_attrDef": "p"
                },
                {
                    "_key": "method",
                    "_value": "",
                    "_type": "kv",
                    "_attrDef": "p"
                },
                {
                    "_key": "target",
                    "_value": "",
                    "_type": "kv",
                    "_attrDef": "p"
                },
                {
                    "_key": "(ngSubmit)",
                    "_value": "",
                    "_type": "kv",
                    "_attrDef": "p"
                },
                {
                    "_key": "(reset)",
                    "_value": "",
                    "_type": "kv",
                    "_attrDef": "p"
                },
                {
                    "_key": "fxFlex",
                    "_value": "50",
                    "_type": "kv",
                    "_attrDef": "c"
                },
                {
                    "_key": "fxLayoutAlign",
                    "_value": "center center",
                    "_type": "kv",
                    "_attrDef": "c"
                }
            ],
            "36eee3c2-1811-9d20-e0b3-7da5f4d2d4d7": {
                "paletteKey": "FlexLayoutCol",
                "parentEditorKey": "05c53111-bfaa-6d25-c7b1-8092e1286990",
                "commentid": null,
                "designerReference": [
                    {
                        "_key": "componentLabel",
                        "_value": "Column",
                        "_type": "kv",
                        "_attrDef": "p",
                        "_useAsLabel": true
                    },
                    {
                        "_key": "style",
                        "_value": "",
                        "_type": "kv",
                        "_attrDef": "p"
                    },
                    {
                        "_key": "class",
                        "_value": [
                            "card-con",
                            "card-form"
                        ],
                        "_type": "dav",
                        "_attrDef": "p"
                    },
                    {
                        "_key": "fxFlex",
                        "_value": "50",
                        "_type": "kv",
                        "_attrDef": "p"
                    },
                    {
                        "_key": "fxLayoutGap",
                        "_value": "",
                        "_type": "kv",
                        "_attrDef": "p"
                    },
                    {
                        "_key": "wrap",
                        "_value": "wrap",
                        "_type": "a",
                        "_attrDef": "p"
                    },
                    {
                        "_key": "layoutAlign",
                        "_value": "start",
                        "_type": "a",
                        "_attrDef": "p"
                    },
                    {
                        "_key": "pLayoutAlign",
                        "_value": "stretch",
                        "_type": "a",
                        "_attrDef": "p"
                    },
                    {
                        "_key": "[fxShow]",
                        "_value": "true",
                        "_type": "kv",
                        "_attrDef": "p"
                    }
                ],
                "3ff9a7db-db38-84bd-d8ce-7b88788b6618": {
                    "paletteKey": "Html5",
                    "parentEditorKey": "36eee3c2-1811-9d20-e0b3-7da5f4d2d4d7",
                    "isAdvancedComponent": true,
                    "commentid": null,
                    "designerReference": [
                        {
                            "_key": "style",
                            "_value": "text-align:center;",
                            "_type": "kv",
                            "_attrDef": "p"
                        },
                        {
                            "_key": "class",
                            "_value": "",
                            "_type": "dav",
                            "_attrDef": "p"
                        },
                        {
                            "_key": "htmlElement",
                            "_value": "p",
                            "_type": "dav",
                            "_attrDef": "p",
                            "_useAsLabel": true
                        },
                        {
                            "_key": "tagType",
                            "_value": "p",
                            "_type": "a",
                            "_attrDef": "p",
                            "_visibility": false
                        },
                        {
                            "_key": "name",
                            "_value": "",
                            "_type": "kv",
                            "_attrDef": "p",
                            "_visibility": false
                        },
                        {
                            "_key": "sandbox",
                            "_value": "",
                            "_type": "kv",
                            "_attrDef": "p",
                            "_visibility": false
                        },
                        {
                            "_key": "src",
                            "_value": "",
                            "_type": "kv",
                            "_attrDef": "p",
                            "_visibility": false
                        },
                        {
                            "_key": "srcdoc",
                            "_value": "",
                            "_type": "kv",
                            "_attrDef": "p",
                            "_visibility": false
                        },
                        {
                            "_key": "width",
                            "_value": "",
                            "_type": "kv",
                            "_attrDef": "p",
                            "_visibility": false
                        },
                        {
                            "_key": "[autoplay]",
                            "_value": "",
                            "_type": "kv",
                            "_attrDef": "p",
                            "_visibility": false
                        },
                        {
                            "_key": "[loop]",
                            "_value": "",
                            "_type": "kv",
                            "_attrDef": "p",
                            "_visibility": false
                        },
                        {
                            "_key": "data",
                            "_value": "",
                            "_type": "kv",
                            "_attrDef": "p",
                            "_visibility": false
                        },
                        {
                            "_key": "audioSource",
                            "_value": [],
                            "_type": "a",
                            "_attrDef": "p",
                            "_visibility": false
                        },
                        {
                            "_key": "videoSource",
                            "_value": [],
                            "_type": "a",
                            "_attrDef": "p",
                            "_visibility": false
                        },
                        {
                            "_key": "audioDatasource",
                            "_value": "",
                            "_type": "a",
                            "_attrDef": "p",
                            "_visibility": false
                        },
                        {
                            "_key": "audioSrc",
                            "_value": "",
                            "_type": "a",
                            "_attrDef": "p",
                            "_visibility": false
                        },
                        {
                            "_key": "audioType",
                            "_value": "",
                            "_type": "a",
                            "_attrDef": "p",
                            "_visibility": false
                        },
                        {
                            "_key": "videoDatasource",
                            "_value": "",
                            "_type": "a",
                            "_attrDef": "p",
                            "_visibility": false
                        },
                        {
                            "_key": "videoSrc",
                            "_value": "",
                            "_type": "a",
                            "_attrDef": "p",
                            "_visibility": false
                        },
                        {
                            "_key": "videoType",
                            "_value": "",
                            "_type": "a",
                            "_attrDef": "p",
                            "_visibility": false
                        },
                        {
                            "_key": "(audioplay)",
                            "_value": "",
                            "_type": "a",
                            "_attrDef": "p",
                            "_visibility": false
                        },
                        {
                            "_key": "(videoplay)",
                            "_value": "",
                            "_type": "a",
                            "_attrDef": "p",
                            "_visibility": false
                        },
                        {
                            "_key": "(audiopause)",
                            "_value": "",
                            "_type": "kv",
                            "_attrDef": "p",
                            "_visibility": false
                        },
                        {
                            "_key": "(videopause)",
                            "_value": "",
                            "_type": "kv",
                            "_attrDef": "p",
                            "_visibility": false
                        },
                        {
                            "_key": "(audioended)",
                            "_value": "",
                            "_type": "kv",
                            "_attrDef": "p",
                            "_visibility": false
                        },
                        {
                            "_key": "(videoended)",
                            "_value": "",
                            "_type": "kv",
                            "_attrDef": "p",
                            "_visibility": false
                        }
                    ],
                    "2b109821-e8c4-9848-3346-e4c6ac6ee754": {
                        "paletteKey": "html-editor",
                        "parentEditorKey": "3ff9a7db-db38-84bd-d8ce-7b88788b6618",
                        "isAdvancedChildComponent": true,
                        "commentid": null,
                        "designerReference": [
                            {
                                "_key": "style",
                                "_value": "",
                                "_type": "kv",
                                "_attrDef": "p"
                            },
                            {
                                "_key": "class",
                                "_value": "",
                                "_type": "dav",
                                "_attrDef": "p"
                            },
                            {
                                "_key": "html",
                                "_value": "<b><center>FORGET PASSWORD</center></b>",
                                "_type": "a",
                                "_attrDef": "p"
                            }
                        ]
                    },
                    "03f27ac1-ef86-e257-7e82-5f65ac57ce82": {
                        "paletteKey": "NG-Input",
                        "parentEditorKey": "3ff9a7db-db38-84bd-d8ce-7b88788b6618",
                        "isAdvancedComponent": true,
                        "commentid": null,
                        "designerReference": [
                            {
                                "_key": "style",
                                "_value": "",
                                "_type": "kv",
                                "_attrDef": "p"
                            },
                            {
                                "_key": "class",
                                "_value": [
                                    "card-form"
                                ],
                                "_type": "dav",
                                "_attrDef": "p"
                            },
                            {
                                "_key": "placeholder",
                                "_value": "New Password",
                                "_type": "kv",
                                "_attrDef": "p",
                                "_useAsLabel": true
                            },
                            {
                                "_key": "value",
                                "_value": "",
                                "_type": "kv",
                                "_attrDef": "p"
                            },
                            {
                                "_key": "[appearance]",
                                "_value": "'outline'",
                                "_type": "a",
                                "_attrDef": "p"
                            },
                            {
                                "_key": "[required]",
                                "_value": "false",
                                "_type": "kv",
                                "_attrDef": "p"
                            },
                            {
                                "_key": "[(ngModel)]",
                                "_value": "",
                                "_type": "kv",
                                "_attrDef": "p"
                            },
                            {
                                "_key": "color",
                                "_value": "",
                                "_type": "kv",
                                "_attrDef": "p"
                            },
                            {
                                "_key": "name",
                                "_value": "",
                                "_type": "kv",
                                "_attrDef": "p"
                            },
                            {
                                "_key": "type",
                                "_value": "",
                                "_type": "kv",
                                "_attrDef": "p"
                            },
                            {
                                "_key": "[formControl]",
                                "_value": "",
                                "_type": "kv",
                                "_attrDef": "p"
                            },
                            {
                                "_key": "readonly",
                                "_value": "",
                                "_type": "kv",
                                "_attrDef": "p"
                            },
                            {
                                "_key": "[disabled]",
                                "_value": "",
                                "_type": "kv",
                                "_attrDef": "p"
                            },
                            {
                                "_key": "id",
                                "_value": "",
                                "_type": "kv",
                                "_attrDef": "p"
                            },
                            {
                                "_key": "[floatLabel]",
                                "_value": "'auto'",
                                "_type": "kv",
                                "_attrDef": "p"
                            },
                            {
                                "_key": "[hideRequiredMarker]",
                                "_value": "false",
                                "_type": "kv",
                                "_attrDef": "p",
                                "_complexity": "advanced"
                            },
                            {
                                "_key": "matError",
                                "_value": [],
                                "_type": "a",
                                "_attrDef": "p",
                                "_visibility": true
                            },
                            {
                                "_key": "inputHint",
                                "_value": [],
                                "_type": "a",
                                "_attrDef": "p",
                                "_visibility": true
                            },
                            {
                                "_key": "Label",
                                "_value": "",
                                "_type": "a",
                                "_attrDef": "p",
                                "_visibility": true
                            },
                            {
                                "_key": "Suffix Icon",
                                "_value": "",
                                "_type": "a",
                                "_attrDef": "p",
                                "_visibility": true
                            },
                            {
                                "_key": "(suffixIconClick)",
                                "_value": "",
                                "_type": "a",
                                "_attrDef": "p",
                                "_visibility": true
                            },
                            {
                                "_key": "Prefix Icon",
                                "_value": "",
                                "_type": "a",
                                "_attrDef": "p",
                                "_visibility": true
                            },
                            {
                                "_key": "(prefixIconClick)",
                                "_value": "",
                                "_type": "a",
                                "_attrDef": "p",
                                "_visibility": true
                            },
                            {
                                "_key": "Prefix",
                                "_value": "",
                                "_type": "a",
                                "_attrDef": "p",
                                "_visibility": true
                            },
                            {
                                "_key": "Suffix",
                                "_value": "",
                                "_type": "a",
                                "_attrDef": "p",
                                "_visibility": true
                            }
                        ]
                    },
                    "3a6d25b3-cb65-ba3f-ecd3-d3a0f63db8f4": {
                        "paletteKey": "NG-Input",
                        "parentEditorKey": "3ff9a7db-db38-84bd-d8ce-7b88788b6618",
                        "isAdvancedComponent": true,
                        "commentid": null,
                        "designerReference": [
                            {
                                "_key": "style",
                                "_value": "",
                                "_type": "kv",
                                "_attrDef": "p"
                            },
                            {
                                "_key": "class",
                                "_value": [
                                    "card-form"
                                ],
                                "_type": "dav",
                                "_attrDef": "p"
                            },
                            {
                                "_key": "placeholder",
                                "_value": "Confirm Password",
                                "_type": "kv",
                                "_attrDef": "p",
                                "_useAsLabel": true
                            },
                            {
                                "_key": "value",
                                "_value": "",
                                "_type": "kv",
                                "_attrDef": "p"
                            },
                            {
                                "_key": "[appearance]",
                                "_value": "'outline'",
                                "_type": "a",
                                "_attrDef": "p"
                            },
                            {
                                "_key": "[required]",
                                "_value": "false",
                                "_type": "kv",
                                "_attrDef": "p"
                            },
                            {
                                "_key": "[(ngModel)]",
                                "_value": "",
                                "_type": "kv",
                                "_attrDef": "p"
                            },
                            {
                                "_key": "color",
                                "_value": "",
                                "_type": "kv",
                                "_attrDef": "p"
                            },
                            {
                                "_key": "name",
                                "_value": "",
                                "_type": "kv",
                                "_attrDef": "p"
                            },
                            {
                                "_key": "type",
                                "_value": "",
                                "_type": "kv",
                                "_attrDef": "p"
                            },
                            {
                                "_key": "[formControl]",
                                "_value": "",
                                "_type": "kv",
                                "_attrDef": "p"
                            },
                            {
                                "_key": "readonly",
                                "_value": "",
                                "_type": "kv",
                                "_attrDef": "p"
                            },
                            {
                                "_key": "[disabled]",
                                "_value": "",
                                "_type": "kv",
                                "_attrDef": "p"
                            },
                            {
                                "_key": "id",
                                "_value": "",
                                "_type": "kv",
                                "_attrDef": "p"
                            },
                            {
                                "_key": "[floatLabel]",
                                "_value": "'auto'",
                                "_type": "kv",
                                "_attrDef": "p"
                            },
                            {
                                "_key": "[hideRequiredMarker]",
                                "_value": "false",
                                "_type": "kv",
                                "_attrDef": "p",
                                "_complexity": "advanced"
                            },
                            {
                                "_key": "matError",
                                "_value": [],
                                "_type": "a",
                                "_attrDef": "p",
                                "_visibility": true
                            },
                            {
                                "_key": "inputHint",
                                "_value": [],
                                "_type": "a",
                                "_attrDef": "p",
                                "_visibility": true
                            },
                            {
                                "_key": "Label",
                                "_value": "",
                                "_type": "a",
                                "_attrDef": "p",
                                "_visibility": true
                            },
                            {
                                "_key": "Suffix Icon",
                                "_value": "",
                                "_type": "a",
                                "_attrDef": "p",
                                "_visibility": true
                            },
                            {
                                "_key": "(suffixIconClick)",
                                "_value": "",
                                "_type": "a",
                                "_attrDef": "p",
                                "_visibility": true
                            },
                            {
                                "_key": "Prefix Icon",
                                "_value": "",
                                "_type": "a",
                                "_attrDef": "p",
                                "_visibility": true
                            },
                            {
                                "_key": "(prefixIconClick)",
                                "_value": "",
                                "_type": "a",
                                "_attrDef": "p",
                                "_visibility": true
                            },
                            {
                                "_key": "Prefix",
                                "_value": "",
                                "_type": "a",
                                "_attrDef": "p",
                                "_visibility": true
                            },
                            {
                                "_key": "Suffix",
                                "_value": "",
                                "_type": "a",
                                "_attrDef": "p",
                                "_visibility": true
                            }
                        ]
                    },
                    "6adda6fb-d3d7-4da3-e18f-6250c2c993a6": {
                        "paletteKey": "NG-button",
                        "parentEditorKey": "3ff9a7db-db38-84bd-d8ce-7b88788b6618",
                        "commentid": null,
                        "designerReference": [
                            {
                                "_key": "style",
                                "_value": "",
                                "_type": "kv",
                                "_attrDef": "p"
                            },
                            {
                                "_key": "class",
                                "_value": [
                                    "but1"
                                ],
                                "_type": "dav",
                                "_attrDef": "p"
                            },
                            {
                                "_key": "buttonname",
                                "_value": "Reset Password",
                                "_type": "a",
                                "_attrDef": "p",
                                "_useAsLabel": true
                            },
                            {
                                "_key": "color",
                                "_value": "",
                                "_type": "kv",
                                "_attrDef": "p"
                            },
                            {
                                "_key": "(click)",
                                "_value": "",
                                "_type": "kv",
                                "_attrDef": "p"
                            },
                            {
                                "_key": "[disabled]",
                                "_value": "",
                                "_type": "kv",
                                "_attrDef": "p"
                            },
                            {
                                "_key": "[disableRipple]",
                                "_value": "",
                                "_type": "kv",
                                "_attrDef": "p"
                            },
                            {
                                "_key": "type",
                                "_value": "",
                                "_type": "kv",
                                "_attrDef": "p"
                            },
                            {
                                "_key": "routerLink",
                                "_value": "/login",
                                "_type": "kv",
                                "_attrDef": "p"
                            }
                        ]
                    }
                }
            }
        }
    }
}
